likeasrt/__init__.py
likeasrt/errors.py
likeasrt/logs.py
likeasrt/main.py
likeasrt/py.typed
likeasrt/commands/__init__.py
likeasrt/commands/srt.py
likeasrt/domain/__init__.py
likeasrt/domain/azurespeech.py
likeasrt/domain/core.py
likeasrt/domain/srt.py
like_a_srt-0.0.4.dist-info/LICENSE
like_a_srt-0.0.4.dist-info/METADATA
like_a_srt-0.0.4.dist-info/WHEEL
like_a_srt-0.0.4.dist-info/entry_points.txt
like_a_srt-0.0.4.dist-info/top_level.txt
like_a_srt-0.0.4.dist-info/RECORD
