Metadata-Version: 2.1
Name: like-a-srt
Version: 0.0.4
Summary: CLI to generate SRT subtitles automatically from audio files, using Azure Speech
Home-page: https://github.com/RobertoPrevato/Like-a-srt
Author: RobertoPrevato
Author-email: roberto.prevato@gmail.com
License: MIT
Keywords: azure speech srt subtitles automatic generation
Platform: UNKNOWN
Classifier: Development Status :: 4 - Beta
Classifier: License :: OSI Approved :: MIT License
Classifier: Programming Language :: Python :: 3
Classifier: Programming Language :: Python :: 3.9
Classifier: Operating System :: OS Independent
License-File: LICENSE
Requires-Dist: click (==8.0.3)
Requires-Dist: essentials (==1.1.4)
Requires-Dist: azure-cognitiveservices-speech (==1.19.0)
Requires-Dist: python-dotenv (==0.19.2)
